aptamer/__init__.py
aptamer/example.py
aptamer/selex.py
aptamer/test.py
aptamer-0.1.3.dist-info/METADATA
aptamer-0.1.3.dist-info/WHEEL
aptamer-0.1.3.dist-info/top_level.txt
aptamer-0.1.3.dist-info/RECORD
