Metadata-Version: 2.4
Name: aptamer
Version: 0.1.3
Summary: Evolve DNA aptamers using RNA folding energy
Requires-Dist: viennarna
Requires-Dist: pytest
Dynamic: requires-dist
Dynamic: summary
